setup.cfg
setup.py
binance_api_test_ancous/Futures.py
binance_api_test_ancous/Spot.py
binance_api_test_ancous/__init__.py
binance_api_test_ancous.egg-info/PKG-INFO
binance_api_test_ancous.egg-info/SOURCES.txt
binance_api_test_ancous.egg-info/dependency_links.txt
binance_api_test_ancous.egg-info/requires.txt
binance_api_test_ancous.egg-info/top_level.txt